faraday_agent_parameters_types/__init__.py
faraday_agent_parameters_types/data_types.py
faraday_agent_parameters_types/faraday_agent_parameters_types.py
faraday_agent_parameters_types/utils.py
faraday_agent_parameters_types/custom_types/__init__.py
faraday_agent_parameters_types/custom_types/faraday_boolean.py
faraday_agent_parameters_types/custom_types/faraday_domains_list.py
faraday_agent_parameters_types/custom_types/faraday_float.py
faraday_agent_parameters_types/custom_types/faraday_int_range.py
faraday_agent_parameters_types/custom_types/faraday_integer.py
faraday_agent_parameters_types/custom_types/faraday_ip.py
faraday_agent_parameters_types/custom_types/faraday_list.py
faraday_agent_parameters_types/custom_types/faraday_password.py
faraday_agent_parameters_types/custom_types/faraday_string.py
faraday_agent_parameters_types/custom_types/faraday_url.py
faraday_agent_parameters_types/static/manifests/arachni-2.0.0.json
faraday_agent_parameters_types/static/manifests/burp-2.0.0.json
faraday_agent_parameters_types/static/manifests/burp-2.0.1.json
faraday_agent_parameters_types/static/manifests/cisco_cybervision-1.0.0.json
faraday_agent_parameters_types/static/manifests/codeql-1.0.0.json
faraday_agent_parameters_types/static/manifests/crackmapexec-2.0.0.json
faraday_agent_parameters_types/static/manifests/dependabot-1.1.0.json
faraday_agent_parameters_types/static/manifests/github_secrets-1.0.0.json
faraday_agent_parameters_types/static/manifests/gvm_openvas-2.0.0.json
faraday_agent_parameters_types/static/manifests/hclappscan-2.6.0.json
faraday_agent_parameters_types/static/manifests/insightvm-2.0.1.json
faraday_agent_parameters_types/static/manifests/microsoft_defender-1.0.0.json
faraday_agent_parameters_types/static/manifests/nessus-2.0.0.json
faraday_agent_parameters_types/static/manifests/nikto2-2.0.0.json
faraday_agent_parameters_types/static/manifests/nikto2-2.1.3.json
faraday_agent_parameters_types/static/manifests/nmap-2.0.0.json
faraday_agent_parameters_types-1.9.1.dist-info/licenses/AUTHORS.rst
faraday_agent_parameters_types-1.9.1.dist-info/licenses/COPYING
faraday_agent_parameters_types-1.9.1.dist-info/METADATA
faraday_agent_parameters_types-1.9.1.dist-info/WHEEL
faraday_agent_parameters_types-1.9.1.dist-info/top_level.txt
faraday_agent_parameters_types-1.9.1.dist-info/RECORD
