Metadata-Version: 2.4
Name: faraday_agent_parameters_types
Version: 1.9.1
Summary: The faraday agents run code remotely to ensure your domains. This info is triggered and published
Home-page: https://github.com/infobyte/faraday_agent_parameters_types
Author: Faraday Development Team
Author-email: devel@infobytesec.com
License: GNU General Public License v3
Keywords: faraday
Classifier: Development Status :: 3 - Alpha
Classifier: Intended Audience :: Developers
Classifier: License :: OSI Approved :: GNU General Public License v3 or later (GPLv3+)
Classifier: Natural Language :: English
Classifier: Programming Language :: Python :: 3
Classifier: Programming Language :: Python :: 3.6
Classifier: Programming Language :: Python :: 3.7
Classifier: Programming Language :: Python :: 3.8
Classifier: Programming Language :: Python :: 3.9
Requires-Python: >=3.7
License-File: COPYING
License-File: AUTHORS.rst
Requires-Dist: marshmallow<4.0.0
Requires-Dist: packaging
Requires-Dist: validators<=0.20.0
Provides-Extra: dev
Requires-Dist: giteasychangelog; extra == "dev"
Requires-Dist: flake8; extra == "dev"
Requires-Dist: pre-commit; extra == "dev"
Requires-Dist: black; extra == "dev"
Provides-Extra: test
Requires-Dist: pytest; extra == "test"
Requires-Dist: pytest-cov; extra == "test"
Provides-Extra: docs
Requires-Dist: mkdocs; extra == "docs"
Requires-Dist: mkdocs-material; extra == "docs"
Dynamic: author
Dynamic: author-email
Dynamic: classifier
Dynamic: description
Dynamic: description-content-type
Dynamic: home-page
Dynamic: keywords
Dynamic: license
Dynamic: license-file
Dynamic: provides-extra
Dynamic: requires-dist
Dynamic: requires-python
Dynamic: summary
